q2data2docx/__init__.py
q2data2docx/excel_format.py
q2data2docx/q2data2docx.py
q2data2docx/version.py
q2data2docx-0.1.38.dist-info/LICENSE
q2data2docx-0.1.38.dist-info/METADATA
q2data2docx-0.1.38.dist-info/WHEEL
q2data2docx-0.1.38.dist-info/RECORD
