Metadata-Version: 2.1
Name: q2data2docx
Version: 0.1.38
Summary: Merging data (XLSX, JSON) and template (DOCX) into resulting DOCX document
Author: Andrei Puchko
Author-email: andrei.puchko@gmx.de
Requires-Python: >=3.7,<4.0
Classifier: Programming Language :: Python :: 3
Classifier: Programming Language :: Python :: 3.7
Classifier: Programming Language :: Python :: 3.8
Classifier: Programming Language :: Python :: 3.9
Classifier: Programming Language :: Python :: 3.10
Classifier: Programming Language :: Python :: 3.11
